onthelam/__init__.py
onthelam/astoperations.py
onthelam/lambdabuilder.py
onthelam/magic.py
on_the_lam-1.2.0.dist-info/LICENSE
on_the_lam-1.2.0.dist-info/METADATA
on_the_lam-1.2.0.dist-info/WHEEL
on_the_lam-1.2.0.dist-info/top_level.txt
on_the_lam-1.2.0.dist-info/RECORD
