Metadata-Version: 2.1
Name: on-the-lam
Version: 1.2.0
Summary: Easier Python lambdas
Home-page: https://github.com/abstiles/onthelam
Author: abstiles
License: UNKNOWN
Project-URL: Bug Tracker, https://github.com/abstiles/onthelam/issues
Platform: UNKNOWN
Classifier: Programming Language :: Python :: 3
Classifier: License :: OSI Approved :: MIT License
Classifier: Operating System :: OS Independent
Requires-Python: >=3.9
License-File: LICENSE
